.gitignore
LICENSE
README.md
setup.cfg
setup.py
requestbin/__init__.py
requestbin/bin.py
requestbin/request.py
requestbin/service.py
requestbin/tools.py
requestbin.egg-info/PKG-INFO
requestbin.egg-info/SOURCES.txt
requestbin.egg-info/dependency_links.txt
requestbin.egg-info/requires.txt
requestbin.egg-info/top_level.txt
test/test.py