Metadata-Version: 1.1
Name: requestbin
Version: 0.3
Summary: a silly wrapper around requestb.in api
Home-page: https://github.com/RedHatQE/requestbin
Author: dparalen
Author-email: UNKNOWN
License: GPLv3+
Platform: UNKNOWN
Classifier: License :: OSI Approved :: GNU General Public License v3 or later (GPLv3+)
Classifier: Programming Language :: Python
Classifier: Topic :: Software Development :: Libraries :: Python Modules
Classifier: Operating System :: POSIX
Classifier: Intended Audience :: Developers
Classifier: Development Status :: 4 - Beta
Provides: requestbin
